cygrid.libs/libgomp-a97153a2.so.1.0.0
cygrid-2.0.4.dist-info/top_level.txt
cygrid-2.0.4.dist-info/METADATA
cygrid-2.0.4.dist-info/WHEEL
cygrid-2.0.4.dist-info/TEMPLATE_LICENCE.rst
cygrid-2.0.4.dist-info/README.rst
cygrid-2.0.4.dist-info/LICENSE.rst
cygrid-2.0.4.dist-info/RECORD
cygrid/hphashtab.pyx
cygrid/kernels.h
cygrid/setup_package.py
cygrid/healpix.cpython-38-x86_64-linux-gnu.so
cygrid/kernels.cpython-38-x86_64-linux-gnu.so
cygrid/helpers.cpython-38-x86_64-linux-gnu.so
cygrid/mock.py
cygrid/hphashtab.cpp
cygrid/cygrid.pyx
cygrid/kernels.cpp
cygrid/version.py
cygrid/helpers.cpp
cygrid/init_testrunner.py
cygrid/kernels.pyx
cygrid/hphashtab.pxd
cygrid/hphashtab.cpython-38-x86_64-linux-gnu.so
cygrid/conftest.py
cygrid/healpix.pyx
cygrid/__init__.py
cygrid/constants.pxd
cygrid/kernels.pxd
cygrid/constants.h
cygrid/helpers.pxd
cygrid/compiler_version.cpython-38-x86_64-linux-gnu.so
cygrid/healpix.cpp
cygrid/_compiler.c
cygrid/healpix.pxd
cygrid/helpers.pyx
cygrid/cygrid.cpp
cygrid/cygrid.cpython-38-x86_64-linux-gnu.so
cygrid/tests/setup_package.py
cygrid/tests/test_healpix.py
cygrid/tests/__init__.py
cygrid/tests/coveragerc
cygrid/tests/test_cygrid.py
cygrid/tests/data/cygrid_test_sightlines.npy
cygrid/tests/data/cygrid_test_maps.npy
