Metadata-Version: 2.1
Name: cygrid
Version: 2.0.4
Summary: cygrid: is a cython-powered convolution-based gridding module for astronomy
Author-email: Benjamin Winkel <bwinkel@mpifr.de>, Lars Flöer <bwinkel@mpifr.de>, Daniel Lenz <mail@daniellenz.org>
License: GPLv3
Project-URL: Homepage, https://pypi.org/project/cygrid/
Project-URL: Documentation, https://bwinkel.github.io/cygrid/
Project-URL: Repository, https://github.com/bwinkel/cygrid
Project-URL: Issues, https://github.com/bwinkel/cygrid/issues
Project-URL: Changelog, https://github.com/bwinkel/cygrid/CHANGES.rst
Keywords: astronomy,science
Classifier: Intended Audience :: Science/Research
Classifier: Development Status :: 4 - Beta
Classifier: Operating System :: OS Independent
Classifier: License :: OSI Approved :: GNU General Public License v3 (GPLv3)
Classifier: Programming Language :: C++
Classifier: Programming Language :: Cython
Classifier: Programming Language :: Python :: 3 :: Only
Classifier: Programming Language :: Python :: Implementation :: CPython
Classifier: Topic :: Scientific/Engineering :: Astronomy
Requires-Python: >=3.8
License-File: licenses/LICENSE.rst
License-File: licenses/README.rst
License-File: licenses/TEMPLATE_LICENCE.rst
Requires-Dist: astropy
Requires-Dist: numpy
Provides-Extra: docs
Requires-Dist: matplotlib ; extra == 'docs'
Requires-Dist: reproject ; extra == 'docs'
Requires-Dist: sphinx ; extra == 'docs'
Requires-Dist: sphinx-astropy[confv2] ; extra == 'docs'
Requires-Dist: sphinx-copybutton ; extra == 'docs'
Requires-Dist: pydata-sphinx-theme ; extra == 'docs'
Requires-Dist: pytest >=7.0 ; extra == 'docs'
Provides-Extra: recommended
Requires-Dist: astroquery ; extra == 'recommended'
Requires-Dist: healpy ; extra == 'recommended'
Requires-Dist: scipy ; extra == 'recommended'
Requires-Dist: matplotlib ; extra == 'recommended'
Provides-Extra: test
Requires-Dist: pytest >=7.0 ; extra == 'test'
Requires-Dist: pytest-astropy >=0.10 ; extra == 'test'
Requires-Dist: pytest-doctestplus ; extra == 'test'
Requires-Dist: healpy ; extra == 'test'
